LICENSE
MANIFEST.in
README.rst
production.ini
setup.py
init.d/mattd.init
mattd/__init__.py
mattd.core.egg-info/PKG-INFO
mattd.core.egg-info/SOURCES.txt
mattd.core.egg-info/dependency_links.txt
mattd.core.egg-info/entry_points.txt
mattd.core.egg-info/namespace_packages.txt
mattd.core.egg-info/not-zip-safe
mattd.core.egg-info/requires.txt
mattd.core.egg-info/top_level.txt
mattd.d/main.ini
mattd/core/__init__.py
mattd/core/app.py
mattd/core/config.py
mattd/core/util.py
mattd/plugins/__init__.py