Metadata-Version: 1.0
Name: mattd.core
Version: 0.0.5
Summary: Voice-driven scriptable daemon.  Matt Daemon.
Home-page: http://mattd.rtfd.org/
Author: Ralph Bean
Author-email: rbean@redhat.com
License: AGPLv3+
Platform: UNKNOWN
